playbacque.py
playbacque-0.2.3.dist-info/METADATA
playbacque-0.2.3.dist-info/WHEEL
playbacque-0.2.3.dist-info/entry_points.txt
playbacque-0.2.3.dist-info/license_files/LICENSE
playbacque-0.2.3.dist-info/RECORD
