Metadata-Version: 2.1
Name: playbacque
Version: 0.2.3
Summary: Loop play audio
Project-URL: Homepage, https://pypi.org/project/playbacque/
Project-URL: Repository, https://github.com/GeeTransit/playbacque
Author-email: George Zhang <geetransit@gmail.com>
License: MIT
Classifier: Development Status :: 3 - Alpha
Classifier: Intended Audience :: End Users/Desktop
Classifier: License :: OSI Approved :: MIT License
Classifier: Operating System :: OS Independent
Classifier: Programming Language :: Python :: 3
Classifier: Topic :: Multimedia :: Sound/Audio :: Players
Requires-Python: <4.0,>=3.7
Requires-Dist: ffmpeg-python<0.3.0,>=0.2.0
Requires-Dist: importlib-metadata<5.0.0,>=4.0.0; python_version < "3.8"
Requires-Dist: sounddevice<0.5.0,>=0.4.0
Requires-Dist: typing-extensions<5.0.0,>=4.0.0; python_version < "3.10"
